urt30arcon/__init__.py
urt30arcon/client.py
urt30arcon/models.py
urt30arcon/protocol.py
urt30arcon/py.typed
urt30arcon-1.2.3.dist-info/LICENSE
urt30arcon-1.2.3.dist-info/WHEEL
urt30arcon-1.2.3.dist-info/METADATA
urt30arcon-1.2.3.dist-info/RECORD
