Metadata-Version: 2.3
Name: urt30arcon
Version: 1.2.3
Summary: Quake3 Async RCON Client
Keywords: Quake3,RCON
Author-email: Urt Thirtyplus <urt30plus@gmail.com>
Requires-Python: >=3.12
Classifier: Development Status :: 4 - Beta
Classifier: License :: OSI Approved :: Apache Software License
Classifier: Intended Audience :: Developers
Project-URL: Home, https://github.com/urt30plus/urt30arcon
Project-URL: Source, https://github.com/urt30plus/urt30arcon
